ecoledirecte_api/__init__.py
ecoledirecte_api/client.py
ecoledirecte_api/const.py
ecoledirecte_api/exceptions.py
ecoledirecte-0.2.3.dist-info/METADATA
ecoledirecte-0.2.3.dist-info/WHEEL
ecoledirecte-0.2.3.dist-info/licenses/LICENSE
ecoledirecte-0.2.3.dist-info/RECORD
