Metadata-Version: 2.4
Name: ecoledirecte
Version: 0.2.3
Summary: Async Python client to interact with Ecole Directe API.
License: LGPL-3.0-or-later
License-File: LICENSE
Author: Giga77
Maintainer: Giga77
Requires-Python: >=3.10,<4.0
Classifier: Programming Language :: Python :: 3.12
Classifier: License :: Free for non-commercial use
Classifier: License :: OSI Approved :: GNU Lesser General Public License v3 (LGPLv3)
Classifier: Natural Language :: French
Classifier: Topic :: Internet :: WWW/HTTP
Requires-Dist: aiohttp (>=3.9.5)
Requires-Dist: backoff (>=1.10.0,<3.0)
Project-URL: Bug Tracker, https://github.com/hacf-fr/ecoledirecte_api/issues
Project-URL: Changelog, https://github.com/hacf-fr/ecoledirecte_api/releases
Project-URL: Homepage, https://github.com/hacf-fr/ecoledirecte_api
Project-URL: Repository, https://github.com/hacf-fr/ecoledirecte_api
